lins_tasks/__init__.py
lins_tasks/tasks.py
lins_tasks/tasksmodel.py
lins_tasks/tasksserializer.py
lins_tasks/tasksview.py
lins_tasks-0.2.0.2.dist-info/METADATA
lins_tasks-0.2.0.2.dist-info/WHEEL
lins_tasks-0.2.0.2.dist-info/top_level.txt
lins_tasks-0.2.0.2.dist-info/RECORD
