Metadata-Version: 2.1
Name: lins-tasks
Version: 0.2.0.2
Summary: Execução de tarefas em segundo plano para django rest framework.
Home-page: https://bitbucket.org/grupolinsferrao/pypck-lins_tasks/
Author: Cristiano Lemos
Author-email: cristianolemos@lojaspompeia.com.br
License: MIT
Platform: UNKNOWN
